linkmerce/.DS_Store
linkmerce/__init__.py
linkmerce/api/.DS_Store
linkmerce/api/__init__.py
linkmerce/api/cj/.DS_Store
linkmerce/api/cj/__init__.py
linkmerce/api/cj/eflexs.py
linkmerce/api/config.py
linkmerce/api/coupang/__init__.py
linkmerce/api/coupang/advertising.py
linkmerce/api/coupang/wing.py
linkmerce/api/ecount/.DS_Store
linkmerce/api/ecount/__init__.py
linkmerce/api/ecount/api.py
linkmerce/api/naver/__init__.py
linkmerce/api/naver/main.py
linkmerce/api/naver/openapi.py
linkmerce/api/sabangnet/__init__.py
linkmerce/api/sabangnet/admin.py
linkmerce/api/searchad/__init__.py
linkmerce/api/searchad/api.py
linkmerce/api/searchad/gfa.py
linkmerce/api/searchad/manage.py
linkmerce/api/smartstore/__init__.py
linkmerce/api/smartstore/api.py
linkmerce/api/smartstore/brand.py
linkmerce/api/smartstore/center.py
linkmerce/common/.DS_Store
linkmerce/common/__init__.py
linkmerce/common/api.py
linkmerce/common/exceptions.py
linkmerce/common/extract.py
linkmerce/common/load.py
linkmerce/common/models.py
linkmerce/common/tasks.py
linkmerce/common/transform.py
linkmerce/core/.DS_Store
linkmerce/core/__init__.py
linkmerce/core/cj/.DS_Store
linkmerce/core/cj/__init__.py
linkmerce/core/cj/eflexs/.DS_Store
linkmerce/core/cj/eflexs/__init__.py
linkmerce/core/cj/eflexs/common.py
linkmerce/core/cj/eflexs/stock/.DS_Store
linkmerce/core/cj/eflexs/stock/__init__.py
linkmerce/core/cj/eflexs/stock/extract.py
linkmerce/core/cj/eflexs/stock/models.sql
linkmerce/core/cj/eflexs/stock/transform.py
linkmerce/core/coupang/.DS_Store
linkmerce/core/coupang/__init__.py
linkmerce/core/coupang/advertising/.DS_Store
linkmerce/core/coupang/advertising/__init__.py
linkmerce/core/coupang/advertising/adreport/.DS_Store
linkmerce/core/coupang/advertising/adreport/__init__.py
linkmerce/core/coupang/advertising/adreport/extract.py
linkmerce/core/coupang/advertising/adreport/models.sql
linkmerce/core/coupang/advertising/adreport/transform.py
linkmerce/core/coupang/advertising/common.py
linkmerce-0.6.4.dist-info/WHEEL
linkmerce-0.6.4.dist-info/METADATA
linkmerce-0.6.4.dist-info/RECORD
