Metadata-Version: 2.3
Name: linkmerce
Version: 0.6.4
Summary: E-commerce API integration management
Requires-Dist: aiohttp>=3.12.15
Requires-Dist: bcrypt>=4.3.0
Requires-Dist: brotli>=1.2.0
Requires-Dist: bs4>=0.0.2
Requires-Dist: duckdb>=1.3.2
Requires-Dist: jinja2>=3.1.6
Requires-Dist: nest-asyncio>=1.6.0
Requires-Dist: openpyxl>=3.1.5
Requires-Dist: pycryptodome>=3.23.0
Requires-Dist: pytz>=2025.2
Requires-Dist: requests>=2.32.4
Requires-Dist: ruamel-yaml==0.18.14
Requires-Dist: tqdm>=4.67.1
Requires-Python: >=3.10
